hapax/__init__.py
hapax/evaluations.py
hapax/monitoring.py
hapax/core/__init__.py
hapax/core/base.py
hapax/core/decorators.py
hapax/core/example.py
hapax/core/flow.py
hapax/core/graph.py
hapax/core/models.py
hapax_docs/README.md
hapax_docs/SUMMARY.md
hapax_docs/__init__.py
hapax_docs/__main__.py
hapax_docs/cli.py
hapax_docs/cursor_setup.py
hapax_docs/debug.py
hapax_docs/indexer.py
hapax_docs/models.py
hapax_docs/prompts.py
hapax_docs/pyproject.toml
hapax_docs/resources.py
hapax_docs/server.py
hapax_docs/tools.py
hapax_docs/version.py
hapax-0.1.7.dist-info/METADATA
hapax-0.1.7.dist-info/WHEEL
hapax-0.1.7.dist-info/entry_points.txt
hapax-0.1.7.dist-info/licenses/LICENSE
hapax-0.1.7.dist-info/RECORD
