Metadata-Version: 2.4
Name: hapax
Version: 0.1.7
Summary: A type-safe graph execution framework built on top of OpenLit for LLM pipelines
License-File: LICENSE
Requires-Python: >=3.11
Requires-Dist: aiohttp>=3.11.13
Requires-Dist: matplotlib>=3.0.0
Requires-Dist: mcp[cli]>=1.3.0
Requires-Dist: networkx>=3.0
Requires-Dist: openai>=1.61.1
Requires-Dist: openlit>=1.33.8
Requires-Dist: opentelemetry-api>=1.21.0
Requires-Dist: opentelemetry-sdk>=1.21.0
Requires-Dist: pydantic>=2.0.0
Requires-Dist: python-dotenv>=1.0.0
Requires-Dist: typing-extensions>=4.0.0
Provides-Extra: assistant
Requires-Dist: mcp[cli]>=1.3.0; extra == 'assistant'
Provides-Extra: dev
Requires-Dist: black>=23.0.0; extra == 'dev'
Requires-Dist: isort>=5.0.0; extra == 'dev'
Requires-Dist: mypy>=1.0.0; extra == 'dev'
Requires-Dist: pytest>=7.0.0; extra == 'dev'
Provides-Extra: docs
Requires-Dist: mcp[cli]>=1.3.0; extra == 'docs'
